{"8r4krpgnMYJj7AVeYBi7og==":"busje-1600x1200.jpg","HIpMC+cYiqUhUakAoWJnQA==":"verhagen%20stuc-en%20schilderwerk%2014-9-1-90x45.png","l5MixstdyreMaAtdQylokQ==":"verhagen%20stuc-en%20schilderwerk%2014-9-1-138x69.png","g57qofJnLHdlQGZ1CVvDSg==":"logo-225x225.png","L7EgXpsdDoulaO5wRuxvPQ==":"logo%20rechthoek-225x113.png","4x5DBtfYXupF24iD2Y22+A==":"logo%20rechthoek%20transparant-225x113.png","2qOFOdYHleEtEuTmoYQ29w==":"brander%20logo%20stukadoor%20en%20saus%20materiaal-400x247.jpg","L42gDBv8LdL0k98ZI1avjw==":"gyproc%20logo%20stukadoor%20materiaal-567x567.png","usQnijuDsK1AaGt4UE3/Pg==":"prinssen%20stuk%20en%20saus%20materiaal-300x149.png","HYyA4wljNnZY6GMsdxPv0A==":"sigma-logo%20schilder%20materiaal-698x203.jpg","LumocU0G8VM3vE8giKgYzg==":"sikkens%20logo%20schilder%20materiaal-512x241.jpg","UoFtXLT4w1Tpz+IuafOwnA==":"knauf%20logo%20stukadoor%20materiaal-225x225.png","poZ2Y+10bvdpoED38SLoXQ==":"stucadoorswerk%20ens-698x524.jpg","hhDxImrDCyj0ZJtw3toKvg==":"stucadoorswerk%20ens%202-960x720.jpg","PJkmuaaEkLnv3v+Rpy4HbQ==":"stucadoorswerk%20ens%203-698x524.jpg","Y40fT/oHyqIh2yhCvUnQWg==":"emmelhage%20schilderwerk-640x480.jpg","dELKrol34cgLR5drdTPc1w==":"emmelhage%20schilderwerk%202-698x524.jpg","dp2yQxy9glzlzt5ykXPqnQ==":"emmelhage%20schilderwerk%203-698x931.jpg","VwIiuaNzugOI6dosly6L/Q==":"schilderwerkzaamheden%20wokrestaurant%20de%20happy%20garden%20kampen%207-698x524.jpg","rCdDaptKW7qeUdkKV19Oug==":"schilderwerkzaamheden%20wokrestaurant%20de%20happy%20garden%20kampen%205-960x720.jpg","if6KPoX1aaofXkjQ1fSJTg==":"schilderwerkzaamheden%20wokrestaurant%20de%20happy%20garden%20kampen-720x960.jpg","fW9RBrh/03KGgYvkz3DbZA==":"kitwerkzaamheden%20ede-698x931.jpg","mppEuRqyy7ku9Ktd7nsZ3A==":"kitwerkzaamheden%20ede%202-698x931.jpg","lZJFrPCUq2Nf1wOqPwb/mg==":"kitwerkzaamheden%20ede%203-698x931.jpg","1UsY3TQRCdROCMwJ0nxhmQ==":"kitwerkzaamheden%20ede%204-698x931.jpg","ustABPYfjFMAMkzCoqbzXQ==":"decoratie%20op%20wanden%201-720x960.jpg","1eDDVEyWMDcwIUga4R8+Qg==":"decoratie%20op%20wanden%202-683x960.jpg","cTBMPxYOWzREcsTRs2tAow==":"saus%20amersfoort%205-960x720.jpg","Os4cPsKC1OrGCVuSGR4OtQ==":"saus%20amersfoort%204-720x960.jpg","+0b5cw1nEd8jpACDLSJVXg==":"saus%20amersfoort%203-960x720.jpg","NR8GL9l/Lki6xZ5/2uxc0A==":"saus%20amersfoort%202-960x720.jpg","S23gInnDGceewGoU1ZUavQ==":"saus%20amersfoort-960x540.jpg","2rTwjbDifNF43mTV1ibg0Q==":"stukadoor%20saus%20ens%205-960x720.jpg","tBFRndjfhpaARNeQ4Nu+LA==":"stukadoor%20saus%20ens%203-960x720.jpg","/fUB2WJ8Zq4m6dEPMJOjrA==":"stukadoor%20saus%20ens%202-720x960.jpg","bIWQQhHfyIO5eT1yRY8c3Q==":"stukadoor%20saus%20ens-720x960.jpg","fogKJiOUvXnPbZqPuPr5rQ==":"homepage%20foto-900x1600.jpg","j/3YlZ61TeUrGD9UKsNY3g==":"sauswerk%20peter-900x1600.jpg","P2qpetBYju9rY27Q4s14dg==":"sauswerk%20peter-666x1184.jpg"}